<annotation>
  <folder>Images</folder>
  <filename>621175187f31478eb8f2c3c106a96ff4.png</filename>
  <size>
    <width>416</width>
    <height>416</height>
    <depth>3</depth>
  </size>
  <segmented>0</segmented>
  <object>
    <name>24</name>
    <pose>Unspecified</pose>
    <truncated>0</truncated>
    <difficult>0</difficult>
    <bndbox>
      <xmin>186</xmin>
      <ymin>188</ymin>
      <xmax>261</xmax>
      <ymax>251</ymax>
    </bndbox>
  </object>
  <object>
    <name>5004</name>
    <pose>Unspecified</pose>
    <truncated>0</truncated>
    <difficult>0</difficult>
    <bndbox>
      <xmin>211</xmin>
      <ymin>208</ymin>
      <xmax>330</xmax>
      <ymax>258</ymax>
    </bndbox>
  </object>
  <object>
    <name>23</name>
    <pose>Unspecified</pose>
    <truncated>0</truncated>
    <difficult>0</difficult>
    <bndbox>
      <xmin>13</xmin>
      <ymin>287</ymin>
      <xmax>74</xmax>
      <ymax>339</ymax>
    </bndbox>
  </object>
</annotation>
