<annotation>
  <folder>Images</folder>
  <filename>c77b71e9adf44957851310d6fabebced.png</filename>
  <size>
    <width>416</width>
    <height>416</height>
    <depth>3</depth>
  </size>
  <segmented>0</segmented>
  <object>
    <name>5003</name>
    <pose>Unspecified</pose>
    <truncated>0</truncated>
    <difficult>0</difficult>
    <bndbox>
      <xmin>13</xmin>
      <ymin>47</ymin>
      <xmax>156</xmax>
      <ymax>107</ymax>
    </bndbox>
  </object>
  <object>
    <name>24</name>
    <pose>Unspecified</pose>
    <truncated>0</truncated>
    <difficult>0</difficult>
    <bndbox>
      <xmin>34</xmin>
      <ymin>172</ymin>
      <xmax>109</xmax>
      <ymax>235</ymax>
    </bndbox>
  </object>
  <object>
    <name>23</name>
    <pose>Unspecified</pose>
    <truncated>0</truncated>
    <difficult>0</difficult>
    <bndbox>
      <xmin>19</xmin>
      <ymin>121</ymin>
      <xmax>96</xmax>
      <ymax>186</ymax>
    </bndbox>
  </object>
</annotation>
