<annotation>
  <folder>Images</folder>
  <filename>ecfd27793ef34fa596350f82b6461c7b.png</filename>
  <size>
    <width>416</width>
    <height>416</height>
    <depth>3</depth>
  </size>
  <segmented>0</segmented>
  <object>
    <name>23</name>
    <pose>Unspecified</pose>
    <truncated>0</truncated>
    <difficult>0</difficult>
    <bndbox>
      <xmin>112</xmin>
      <ymin>86</ymin>
      <xmax>182</xmax>
      <ymax>145</ymax>
    </bndbox>
  </object>
  <object>
    <name>5004</name>
    <pose>Unspecified</pose>
    <truncated>0</truncated>
    <difficult>0</difficult>
    <bndbox>
      <xmin>263</xmin>
      <ymin>49</ymin>
      <xmax>380</xmax>
      <ymax>98</ymax>
    </bndbox>
  </object>
  <object>
    <name>5004</name>
    <pose>Unspecified</pose>
    <truncated>0</truncated>
    <difficult>0</difficult>
    <bndbox>
      <xmin>243</xmin>
      <ymin>123</ymin>
      <xmax>371</xmax>
      <ymax>177</ymax>
    </bndbox>
  </object>
</annotation>
